MANIFEST.in
README.rst
setup.py
daguerre/__init__.py
daguerre/adjustments.py
daguerre/helpers.py
daguerre/models.py
daguerre/urls.py
daguerre/utils.py
daguerre/views.py
daguerre/widgets.py
daguerre/management/__init__.py
daguerre/management/commands/__init__.py
daguerre/management/commands/_daguerre_clean.py
daguerre/management/commands/_daguerre_preadjust.py
daguerre/management/commands/daguerre.py
daguerre/migrations/0001_initial.py
daguerre/migrations/0002_auto_20140904_2006.py
daguerre/migrations/0003_auto_20160301_2342.py
daguerre/migrations/0004_hash_upload_to_dir.py
daguerre/migrations/__init__.py
daguerre/static/daguerre/css/areawidget.css
daguerre/static/daguerre/js/areawidget.daguerre.js
daguerre/static/imgareaselect/GPL-LICENSE.txt
daguerre/static/imgareaselect/MIT-LICENSE.txt
daguerre/static/imgareaselect/css/border-anim-h.gif
daguerre/static/imgareaselect/css/border-anim-v.gif
daguerre/static/imgareaselect/css/imgareaselect-animated.css
daguerre/static/imgareaselect/scripts/jquery.imgareaselect.js
daguerre/static/imgareaselect/scripts/jquery.imgareaselect.min.js
daguerre/static/imgareaselect/scripts/jquery.min.js
daguerre/templatetags/__init__.py
daguerre/templatetags/daguerre.py
daguerre/tests/__init__.py
daguerre/tests/base.py
daguerre/tests/data/100x100.png
daguerre/tests/data/100x50.psd
daguerre/tests/data/100x50_crop.png
daguerre/tests/data/20x7_exif_not_rotated.jpg
daguerre/tests/data/20x7_exif_rotated.jpg
daguerre/tests/data/20x7_no_exif.jpg
daguerre/tests/data/20x7_no_exif.png
daguerre/tests/data/25x25_fit_named_crop.png
daguerre/tests/data/50x100_crop.png
daguerre/tests/data/50x40_fill.png
daguerre/tests/data/50x50_crop.png
daguerre/tests/data/50x50_crop_area.png
daguerre/tests/data/50x50_fit.png
daguerre/tests/data/broken.png
daguerre/tests/functional/__init__.py
daguerre/tests/functional/test_adjustments.py
daguerre/tests/functional/test_templatetags.py
daguerre/tests/unit/__init__.py
daguerre/tests/unit/test_adjustments.py
django_daguerre.egg-info/PKG-INFO
django_daguerre.egg-info/SOURCES.txt
django_daguerre.egg-info/dependency_links.txt
django_daguerre.egg-info/not-zip-safe
django_daguerre.egg-info/requires.txt
django_daguerre.egg-info/top_level.txt
